ds_create/__init__.py
ds_create-0.2.1.data/scripts/ds-create
ds_create-0.2.1.dist-info/LICENSE
ds_create-0.2.1.dist-info/METADATA
ds_create-0.2.1.dist-info/WHEEL
ds_create-0.2.1.dist-info/top_level.txt
ds_create-0.2.1.dist-info/RECORD
