Metadata-Version: 2.1
Name: ds-create
Version: 0.2.1
Summary: A simple CLI program for creating program templates.
Home-page: https://github.com/a-poor/ds-create
Author: Austin Poor
Author-email: austinpoor@gmail.com
License: UNKNOWN
Platform: UNKNOWN
Classifier: Programming Language :: Python :: 3
Classifier: License :: OSI Approved :: GNU General Public License v3 (GPLv3)
Classifier: Operating System :: OS Independent
Requires-Python: >=3.6
